plotlyplus/__init__.py
plotlyplus/plotlyplus.py
plotlyplus/plotlyplus_safe.py
tests/__init__.py
plotlyplus-0.1.1.dist-info/LICENSE
plotlyplus-0.1.1.dist-info/METADATA
plotlyplus-0.1.1.dist-info/WHEEL
plotlyplus-0.1.1.dist-info/top_level.txt
plotlyplus-0.1.1.dist-info/RECORD
