Metadata-Version: 2.1
Name: plotlyplus
Version: 0.1.1
Summary: Enhance pandas DataFrame with direct Plotly Express plotting functions
Home-page: https://github.com/jgbrainstorm/plotlyplus
Author: Jiangang Hao
Author-email: jgbrainstorm@gmail.com
Classifier: Programming Language :: Python :: 3
Classifier: License :: OSI Approved :: MIT License
Classifier: Operating System :: OS Independent
Requires-Python: >=3.6
License-File: LICENSE
Requires-Dist: pandas >=1.0.0
Requires-Dist: plotly >=4.0.0
